setup.py
TN/__init__.py
TN/aprendizaje.py
TN/carbono.py
TN/enanablanca.py
TN/enso.py
TN/logistico.py
TN/mezcla.py
TN/nolinyestrelas.py
TN/omori.py
TN/orbita.py
TN/vanderpol.py
TN/zombies.py
TN2601.egg-info/PKG-INFO
TN2601.egg-info/SOURCES.txt
TN2601.egg-info/dependency_links.txt
TN2601.egg-info/not-zip-safe
TN2601.egg-info/top_level.txt