Metadata-Version: 2.1
Name: TN2601
Version: 1.1
Summary: Librería para poder chequear ejercicios propuestos del libro numérico versión 2022.
Home-page: UNKNOWN
Author: Axel Osses A. & Diego Olguín W.
License: UNKNOWN
Platform: UNKNOWN
